{ "compressionlevel":-1,
 "height":16,
 "infinite":false,
 "layers":[
        {
         "data":[0, 0, 0, 0, 0, 0, 0, 0, 0, 0, 0, 0, 0, 0, 0, 0, 0, 0, 0, 0, 0, 0, 0, 0, 0, 0, 0, 0, 0, 0, 0, 0,
            0, 243, 244, 245, 246, 243, 244, 245, 246, 243, 244, 245, 246, 243, 244, 243, 244, 245, 246, 243, 244, 245, 246, 245, 246, 243, 244, 245, 246, 0, 0, 0,
            0, 247, 248, 249, 250, 247, 248, 249, 250, 247, 248, 249, 250, 247, 248, 247, 248, 249, 250, 247, 248, 249, 250, 249, 250, 247, 248, 249, 250, 0, 0, 0,
            0, 251, 252, 253, 254, 251, 252, 253, 254, 251, 252, 253, 254, 251, 252, 251, 252, 253, 254, 251, 252, 253, 254, 253, 254, 251, 252, 253, 254, 0, 0, 0,
            0, 255, 256, 257, 258, 255, 256, 257, 258, 255, 256, 257, 258, 255, 256, 255, 256, 257, 258, 255, 256, 257, 258, 257, 258, 255, 256, 257, 258, 0, 0, 0,
            0, 243, 244, 245, 246, 243, 244, 245, 246, 243, 244, 245, 246, 243, 244, 243, 244, 245, 246, 245, 246, 243, 244, 245, 246, 243, 244, 245, 246, 0, 0, 0,
            0, 247, 248, 249, 250, 247, 248, 249, 250, 247, 248, 249, 250, 247, 248, 247, 248, 249, 250, 249, 250, 247, 248, 249, 250, 247, 248, 249, 250, 0, 0, 0,
            0, 251, 252, 253, 254, 251, 252, 253, 254, 251, 252, 253, 254, 251, 252, 251, 252, 253, 254, 253, 254, 251, 252, 253, 254, 251, 252, 253, 254, 0, 0, 0,
            0, 255, 256, 257, 258, 255, 256, 257, 258, 255, 256, 257, 258, 255, 256, 255, 256, 257, 258, 257, 258, 255, 256, 257, 258, 255, 256, 257, 258, 0, 0, 0,
            244, 245, 246, 243, 244, 245, 246, 243, 244, 245, 246, 243, 244, 245, 246, 243, 244, 245, 246, 243, 244, 245, 246, 243, 244, 245, 246, 243, 244, 245, 246, 0,
            248, 249, 250, 247, 248, 249, 250, 247, 248, 249, 250, 247, 248, 249, 250, 247, 248, 249, 250, 247, 248, 249, 250, 247, 248, 249, 250, 247, 248, 249, 250, 0,
            252, 253, 254, 251, 252, 253, 254, 251, 252, 253, 254, 251, 252, 253, 254, 251, 252, 253, 254, 251, 252, 253, 254, 251, 252, 253, 254, 251, 252, 253, 254, 0,
            256, 257, 258, 255, 256, 257, 258, 255, 256, 257, 258, 255, 256, 257, 258, 255, 256, 257, 258, 255, 256, 257, 258, 255, 256, 257, 258, 255, 256, 257, 258, 0,
            0, 243, 244, 245, 246, 243, 244, 245, 246, 243, 244, 245, 246, 243, 244, 245, 246, 243, 244, 245, 246, 243, 244, 245, 246, 243, 244, 245, 246, 0, 0, 0,
            0, 247, 248, 249, 250, 247, 248, 249, 250, 247, 248, 249, 250, 247, 248, 249, 250, 247, 248, 249, 250, 247, 248, 249, 250, 247, 248, 249, 250, 0, 0, 0,
            0, 251, 252, 253, 254, 251, 252, 253, 254, 251, 252, 253, 254, 251, 252, 253, 254, 251, 252, 253, 254, 251, 252, 253, 254, 251, 252, 253, 254, 0, 0, 0],
         "height":16,
         "id":2,
         "name":"background",
         "opacity":1,
         "type":"tilelayer",
         "visible":false,
         "width":32,
         "x":0,
         "y":0
        }, 
        {
         "draworder":"topdown",
         "id":4,
         "name":"collectibles",
         "objects":[
                {
                 "height":0,
                 "id":5,
                 "name":"",
                 "point":true,
                 "rotation":0,
                 "type":"",
                 "visible":true,
                 "width":0,
                 "x":57.5199,
                 "y":116.055
                }, 
                {
                 "height":0,
                 "id":6,
                 "name":"",
                 "point":true,
                 "rotation":0,
                 "type":"",
                 "visible":true,
                 "width":0,
                 "x":81.5429,
                 "y":115.716
                }, 
                {
                 "height":0,
                 "id":7,
                 "name":"",
                 "point":true,
                 "rotation":0,
                 "type":"",
                 "visible":true,
                 "width":0,
                 "x":101.506,
                 "y":116.055
                }, 
                {
                 "height":0,
                 "id":9,
                 "name":"",
                 "point":true,
                 "rotation":0,
                 "type":"",
                 "visible":true,
                 "width":0,
                 "x":68.0088,
                 "y":96.7687
                }, 
                {
                 "height":0,
                 "id":10,
                 "name":"",
                 "point":true,
                 "rotation":0,
                 "type":"",
                 "visible":true,
                 "width":0,
                 "x":91.6935,
                 "y":97.4454
                }, 
                {
                 "height":0,
                 "id":11,
                 "name":"",
                 "point":true,
                 "rotation":0,
                 "type":"",
                 "visible":true,
                 "width":0,
                 "x":79.8511,
                 "y":79.1744
                }, 
                {
                 "height":0,
                 "id":12,
                 "name":"",
                 "point":true,
                 "rotation":0,
                 "type":"",
                 "visible":true,
                 "width":0,
                 "x":152.935,
                 "y":82.5579
                }, 
                {
                 "height":0,
                 "id":13,
                 "name":"",
                 "point":true,
                 "rotation":0,
                 "type":"",
                 "visible":true,
                 "width":0,
                 "x":174.928,
                 "y":81.8812
                }, 
                {
                 "height":0,
                 "id":14,
                 "name":"",
                 "point":true,
                 "rotation":0,
                 "type":"",
                 "visible":true,
                 "width":0,
                 "x":198.951,
                 "y":81.8812
                }, 
                {
                 "height":0,
                 "id":15,
                 "name":"",
                 "point":true,
                 "rotation":0,
                 "type":"",
                 "visible":true,
                 "width":0,
                 "x":226.696,
                 "y":81.2045
                }, 
                {
                 "height":0,
                 "id":16,
                 "name":"",
                 "point":true,
                 "rotation":0,
                 "type":"",
                 "visible":true,
                 "width":0,
                 "x":162.409,
                 "y":64.2869
                }, 
                {
                 "height":0,
                 "id":17,
                 "name":"",
                 "point":true,
                 "rotation":0,
                 "type":"",
                 "visible":true,
                 "width":0,
                 "x":187.109,
                 "y":65.302
                }, 
                {
                 "height":0,
                 "id":18,
                 "name":"",
                 "point":true,
                 "rotation":0,
                 "type":"",
                 "visible":true,
                 "width":0,
                 "x":217.222,
                 "y":63.6102
                }, 
                {
                 "height":0,
                 "id":19,
                 "name":"",
                 "point":true,
                 "rotation":0,
                 "type":"",
                 "visible":true,
                 "width":0,
                 "x":198.613,
                 "y":44.3241
                }, 
                {
                 "height":0,
                 "id":20,
                 "name":"",
                 "point":true,
                 "rotation":0,
                 "type":"",
                 "visible":true,
                 "width":0,
                 "x":174.59,
                 "y":45.3392
                }, 
                {
                 "height":0,
                 "id":21,
                 "name":"",
                 "point":true,
                 "rotation":0,
                 "type":"",
                 "visible":true,
                 "width":0,
                 "x":188.124,
                 "y":26.7298
                }],
         "opacity":1,
         "type":"objectgroup",
         "visible":true,
         "x":0,
         "y":0
        }, 
        {
         "draworder":"topdown",
         "id":5,
         "name":"player",
         "objects":[
                {
                 "height":0,
                 "id":22,
                 "name":"PlayerSpawn",
                 "point":true,
                 "rotation":0,
                 "type":"",
                 "visible":true,
                 "width":0,
                 "x":263.649,
                 "y":186.628
                }],
         "opacity":1,
         "type":"objectgroup",
         "visible":true,
         "x":0,
         "y":0
        }, 
        {
         "data":[91, 46, 46, 46, 46, 46, 46, 46, 46, 46, 46, 46, 46, 46, 46, 46, 46, 46, 46, 46, 46, 46, 46, 46, 46, 46, 46, 46, 46, 3221225498, 112, 112,
            113, 36, 37, 35, 0, 0, 0, 0, 0, 0, 0, 0, 0, 0, 0, 0, 0, 0, 0, 0, 0, 0, 0, 0, 0, 0, 0, 0, 35, 111, 112, 112,
            113, 58, 59, 0, 0, 0, 0, 0, 0, 0, 0, 0, 0, 0, 0, 0, 0, 0, 0, 0, 0, 0, 0, 0, 0, 0, 0, 36, 37, 111, 112, 112,
            113, 0, 0, 0, 0, 0, 0, 0, 0, 0, 0, 0, 0, 0, 0, 0, 0, 0, 0, 0, 0, 0, 0, 0, 0, 0, 0, 58, 59, 111, 112, 112,
            113, 0, 0, 0, 0, 0, 0, 0, 0, 0, 0, 0, 0, 0, 0, 0, 0, 0, 0, 0, 0, 0, 0, 0, 0, 0, 0, 0, 0, 111, 112, 112,
            113, 0, 0, 0, 0, 0, 0, 0, 0, 0, 0, 0, 0, 0, 0, 0, 0, 0, 0, 0, 0, 0, 0, 0, 0, 0, 0, 0, 0, 111, 112, 112,
            113, 0, 0, 0, 0, 0, 0, 0, 0, 13, 14, 14, 14, 15, 35, 0, 0, 0, 0, 0, 0, 0, 0, 0, 0, 0, 0, 0, 0, 111, 112, 112,
            113, 0, 0, 0, 0, 0, 0, 0, 0, 0, 0, 0, 0, 0, 0, 0, 0, 0, 0, 0, 0, 0, 0, 0, 0, 0, 0, 0, 0, 111, 112, 112,
            113, 0, 0, 13, 14, 14, 15, 0, 0, 0, 0, 0, 0, 0, 0, 0, 0, 0, 0, 0, 0, 0, 0, 0, 0, 0, 0, 0, 0, 133, 134, 93,
            113, 0, 0, 0, 0, 0, 0, 0, 0, 0, 0, 0, 0, 0, 0, 0, 0, 0, 0, 0, 0, 0, 0, 0, 0, 0, 0, 0, 0, 0, 0, 111,
            113, 0, 0, 0, 0, 0, 0, 0, 0, 0, 0, 0, 0, 0, 0, 0, 0, 0, 0, 0, 0, 0, 0, 0, 0, 0, 0, 0, 0, 49, 50, 111,
            113, 0, 0, 0, 0, 0, 0, 0, 0, 0, 0, 0, 0, 0, 0, 0, 0, 0, 0, 0, 7, 8, 9, 0, 0, 0, 0, 0, 0, 7, 8, 111,
            113, 299, 299, 299, 300, 0, 0, 0, 0, 0, 0, 0, 0, 0, 7, 8, 8, 8, 8, 8, 33, 30, 31, 0, 0, 0, 0, 7, 8, 33, 30, 111,
            113, 0, 0, 0, 0, 0, 0, 0, 0, 0, 0, 0, 0, 0, 29, 30, 30, 30, 30, 30, 30, 30, 32, 8, 9, 0, 0, 29, 30, 30, 31, 111,
            135, 0, 0, 0, 0, 0, 0, 0, 0, 0, 0, 0, 7, 8, 33, 30, 30, 30, 30, 30, 30, 30, 30, 30, 32, 8, 8, 8, 33, 30, 35, 111,
            1073741870, 2, 2, 2, 2, 2, 2, 2, 2, 2, 2, 2, 2, 2, 2, 2, 2, 2, 2, 2, 2, 2, 2, 2, 2, 2, 2, 2, 2, 2, 2, 2],
         "height":16,
         "id":1,
         "name":"world",
         "opacity":1,
         "type":"tilelayer",
         "visible":true,
         "width":32,
         "x":0,
         "y":0
        }],
 "nextlayerid":6,
 "nextobjectid":23,
 "orientation":"orthogonal",
 "renderorder":"right-down",
 "tiledversion":"1.11.2",
 "tileheight":16,
 "tilesets":[
        {
         "columns":22,
         "firstgid":1,
         "image":"terrain.png",
         "imageheight":176,
         "imagewidth":352,
         "margin":0,
         "name":"terrain",
         "spacing":0,
         "tilecount":242,
         "tileheight":16,
         "tilewidth":16
        }, 
        {
         "columns":4,
         "firstgid":243,
         "image":"Blue.png",
         "imageheight":64,
         "imagewidth":64,
         "margin":0,
         "name":"Blue back",
         "spacing":0,
         "tilecount":16,
         "tileheight":16,
         "tilewidth":16
        }, 
        {
         "firstgid":259,
         "source":"terrain.tsx"
        }],
 "tilewidth":16,
 "type":"map",
 "version":"1.10",
 "width":32
}